{
	"title": "Deadeye Sniper",
	"author": "Zerthox",
	"link": "https://github.com/Zerthox",
	"date": "26/04/2017",
	"patch": "1.6",
	"tags": ["pvp", "sniper", "deadeye"],
	"build": {
		"weapons": {
			"primary": {
				"name": "Surplus SVD",
				"talents": ["Competent", "Deadly", "Unforgiving"],
				"mods": {
					"magazine": ["Magazine Size", "Rate of Fire", "Critical Hit Damage"],
					"underbarrel": ["Critical Hit Damage", "Reload Speed", "Stability"],
					"muzzle": ["Critical Hit Damage", "Stability", "Accuracy"],
					"scope": ["Critical Hit Damage", "Stability", "Accuracy"]
				},
				"icon": "svd"
			},
			"secondary": {
				"name": "M700",
				"talents": ["Competent", "Deadly", "Prepared"],
				"mods": {
					"magazine": ["Magazine Size", "Rate of Fire", "Critical Hit Damage"],
					"underbarrel": ["Critical Hit Damage", "Reload Speed", "Accuracy"],
					"muzzle": ["Critical Hit Damage", "Accuracy", "Stability"],
					"scope": ["Critical Hit Damage", "Accuracy", "Stability"]
				},
				"icon": "m700"
			}
		},
		"gear": {
			"items": {
				"chest": {
					"name": "Reckless Chest",
					"rolls": ["Health", "Skill Haste", "Burn Resistance"],
					"icon": "he"
				},
				"backpack": {
					"name": "Specialized Backpack",
					"rolls": ["Health", "Burn Resistance"],
					"icon": "he"
				},
				"mask": {
					"name": "DeadEYE Mask",
					"rolls": ["Health", "Burn Resistance"],
					"icon": "deadeye"
				},
				"gloves": {
					"name": "DeadEYE Gloves",
					"rolls": ["Marksman Rifle Damage", "Critical Hit Damage", "Skill Haste"],
					"icon": "deadeye"
				},
				"holster": {
					"name": "DeadEYE Holster",
					"rolls": ["Health"],
					"icon": "deadeye"
				},
				"knee-pads": {
					"name": "DeadEYE Knee Pads",
					"rolls": ["Health", "Burn Resistance", "Shock Resistance", "Disrupt Resistance"],
					"icon": "deadeye"
				}
			},
			"stats": {
				"main-stats": {
					"4x": "Firearms",
					"1x": "Electronics"
				},
				"mods": {
					"5x": ["Firearms", "Health"]
				},
				"performance": {
					"4x": {
						"name": "First Aid Self Heal",
						"icon": "first-aid"
					}
				}
			}
		},
		"skills": {
			"1": {
				"name": "First Aid",
				"mod": "Booster Shot"
			},
			"2": {
				"name": "Pulse",
				"mod": "Tactical Scanner"
			},
			"link": {
				"mod": "Survivor Link"
			}
		}
	}
}
